napari_arboretum/__init__.py
napari_arboretum/_hookimpls.py
napari_arboretum/_version.py
napari_arboretum/graph.py
napari_arboretum/napari.yaml
napari_arboretum/plugin.py
napari_arboretum/tree.py
napari_arboretum/util.py
napari_arboretum/io/__init__.py
napari_arboretum/io/svg.py
napari_arboretum/sample/registry.txt
napari_arboretum/sample/sample_data.py
napari_arboretum/visualisation/base_plotter.py
napari_arboretum/visualisation/matplotlib_plotter.py
napari_arboretum/visualisation/vispy_plotter.py
napari_arboretum-0.2.0.dist-info/licenses/LICENSE.md
napari_arboretum-0.2.0.dist-info/METADATA
napari_arboretum-0.2.0.dist-info/WHEEL
napari_arboretum-0.2.0.dist-info/entry_points.txt
napari_arboretum-0.2.0.dist-info/top_level.txt
napari_arboretum-0.2.0.dist-info/RECORD
