Metadata-Version: 2.4
Name: napari-arboretum
Version: 0.2.0
Summary: Track graph and lineage tree visualization with napari
Author-email: "Alan R. Lowe" <a.lowe@ucl.ac.uk>
Project-URL: homepage, https://github.com/lowe-lab-ucl/arboretum
Classifier: Development Status :: 4 - Beta
Classifier: Framework :: napari
Classifier: Intended Audience :: Developers
Classifier: License :: OSI Approved :: BSD License
Classifier: Operating System :: OS Independent
Classifier: Programming Language :: Python :: 3
Classifier: Programming Language :: Python :: 3.10
Classifier: Programming Language :: Python :: 3.11
Classifier: Programming Language :: Python :: 3.12
Classifier: Programming Language :: Python :: 3.13
Classifier: Programming Language :: Python
Classifier: Topic :: Scientific/Engineering :: Visualization
Requires-Python: >=3.10
License-File: LICENSE.md
Requires-Dist: matplotlib
Requires-Dist: napari-matplotlib>=0.2.1
Requires-Dist: napari>=0.6.0
Requires-Dist: numpy>=1.17.3
Requires-Dist: pandas
Requires-Dist: pooch>=1
Requires-Dist: qtpy
Requires-Dist: scikit-image
Requires-Dist: vispy
Dynamic: license-file
